arp_jarvis_composite_executor-0.3.8.dist-info/licenses/LICENSE
jarvis_composite_executor/__init__.py
jarvis_composite_executor/__main__.py
jarvis_composite_executor/app.py
jarvis_composite_executor/auth.py
jarvis_composite_executor/config.py
jarvis_composite_executor/executor.py
jarvis_composite_executor/llm_assets.py
jarvis_composite_executor/schema_utils.py
jarvis_composite_executor/utils.py
jarvis_composite_executor/clients/__init__.py
jarvis_composite_executor/clients/interfaces.py
jarvis_composite_executor/clients/node_registry.py
jarvis_composite_executor/clients/run_coordinator.py
jarvis_composite_executor/clients/selection.py
jarvis_composite_executor/engine/__init__.py
jarvis_composite_executor/engine/arggen.py
jarvis_composite_executor/engine/binder.py
jarvis_composite_executor/engine/driver.py
jarvis_composite_executor/engine/planner.py
scripts/send_request.py
arp_jarvis_composite_executor-0.3.8.dist-info/METADATA
arp_jarvis_composite_executor-0.3.8.dist-info/WHEEL
arp_jarvis_composite_executor-0.3.8.dist-info/entry_points.txt
arp_jarvis_composite_executor-0.3.8.dist-info/top_level.txt
arp_jarvis_composite_executor-0.3.8.dist-info/RECORD
